resms/__init__.py
resms/_client.py
resms/otp/__init__.py
resms/otp/service.py
resms/sms/__init__.py
resms/sms/service.py
resms-0.3.2.dist-info/METADATA
resms-0.3.2.dist-info/WHEEL
resms-0.3.2.dist-info/licenses/LICENSE.txt
resms-0.3.2.dist-info/RECORD
