Metadata-Version: 2.4
Name: resms
Version: 0.3.2
Summary: Python SDK for ReSMS, a simple and powerful SMS API.
Project-URL: Documentation, https://github.com/resms/resms-python#readme
Project-URL: Issues, https://github.com/resms/resms-python/issues
Project-URL: Source, https://github.com/resms/resms-python
Author-email: louanbel <louanbelicaud63@gmail.com>
License-Expression: MIT
License-File: LICENSE.txt
Classifier: Development Status :: 4 - Beta
Classifier: Programming Language :: Python
Classifier: Programming Language :: Python :: 3.9
Classifier: Programming Language :: Python :: 3.10
Classifier: Programming Language :: Python :: 3.11
Classifier: Programming Language :: Python :: 3.12
Classifier: Programming Language :: Python :: Implementation :: CPython
Requires-Python: >=3.9
Requires-Dist: requests>=2.32.4
Provides-Extra: dev
Requires-Dist: mypy; extra == 'dev'
Requires-Dist: ruff; extra == 'dev'
Requires-Dist: types-requests; extra == 'dev'
